blazefl/__init__.py
blazefl/py.typed
blazefl/contrib/__init__.py
blazefl/contrib/fedavg.py
blazefl/core/__init__.py
blazefl/core/__init__.pyi
blazefl/core/client_trainer.py
blazefl/core/client_trainer.pyi
blazefl/core/model_selector.py
blazefl/core/model_selector.pyi
blazefl/core/partitioned_dataset.py
blazefl/core/partitioned_dataset.pyi
blazefl/core/server_handler.py
blazefl/core/server_handler.pyi
blazefl/core/utils.py
blazefl/core/utils.pyi
blazefl/reproducibility/__init__.py
blazefl/reproducibility/__init__.pyi
blazefl/reproducibility/generator.py
blazefl/reproducibility/generator.pyi
blazefl/reproducibility/snapshot.py
blazefl/reproducibility/snapshot.pyi
blazefl-2.0.3.dist-info/METADATA
blazefl-2.0.3.dist-info/WHEEL
blazefl-2.0.3.dist-info/licenses/LICENSE
blazefl-2.0.3.dist-info/RECORD
