Metadata-Version: 2.4
Name: blazefl
Version: 2.0.3
Summary: A blazing-fast, minimalist, and researcher-friendly simulation framework for Federated Learning.
Author-email: kitsuyaazuma <kitsuyaazuma@gmail.com>
License-File: LICENSE
Classifier: License :: OSI Approved :: Apache Software License
Classifier: Programming Language :: Python
Classifier: Programming Language :: Python :: 3 :: Only
Classifier: Programming Language :: Python :: 3.12
Classifier: Programming Language :: Python :: 3.13
Classifier: Programming Language :: Python :: 3.14
Requires-Python: >=3.12
Requires-Dist: torch>=2.8.0
Provides-Extra: contrib
Requires-Dist: tqdm>=4.67.1; extra == 'contrib'
Provides-Extra: reproducibility
Requires-Dist: numpy>=2.3.1; extra == 'reproducibility'
